<?xml version="1.0" encoding ="utf-8"?>
<root>
  <!-- 0 -->
  <char id="0">
    <x>18</x>
    <y>8</y>
    <width>28</width>
    <height>48</height>
  </char>
  <!-- 1 -->
  <char id="1">
    <x>82</x>
    <y>8</y>
    <width>28</width>
    <height>48</height>
  </char>
  <!-- 2 -->
  <char id="2">
    <x>146</x>
    <y>8</y>
    <width>28</width>
    <height>48</height>
  </char>
  <!-- 3 -->
  <char id="3">
    <x>210</x>
    <y>8</y>
    <width>28</width>
    <height>48</height>
  </char>
  <!-- 4 -->
  <char id="4">
    <x>274</x>
    <y>8</y>
    <width>28</width>
    <height>48</height>
  </char>
  <!-- 5 -->
  <char id="5">
    <x>338</x>
    <y>8</y>
    <width>28</width>
    <height>48</height>
  </char>
  <!-- 6 -->
  <char id="6">
    <x>402</x>
    <y>8</y>
    <width>28</width>
    <height>48</height>
  </char>
  <!-- . -->
  <char id=".">
    <x>466</x>
    <y>8</y>
    <width>6</width>
    <height>48</height>
  </char>
  <!-- A -->
  <char id="A">
    <x>530</x>
    <y>8</y>
    <width>28</width>
    <height>48</height>
  </char>
  <!-- B -->
  <char id="B">
    <x>594</x>
    <y>8</y>
    <width>28</width>
    <height>48</height>
  </char>
  <!-- C -->
  <char id="C">
    <x>658</x>
    <y>8</y>
    <width>28</width>
    <height>48</height>
  </char>
  <!-- E -->
  <char id="E">
    <x>722</x>
    <y>8</y>
    <width>28</width>
    <height>48</height>
  </char>
  <!-- L -->
  <char id="L">
    <x>786</x>
    <y>8</y>
    <width>28</width>
    <height>48</height>
  </char>
  <!-- N -->
  <char id="N">
    <x>850</x>
    <y>8</y>
    <width>28</width>
    <height>48</height>
  </char>
  <!-- O -->
  <char id="O">
    <x>914</x>
    <y>8</y>
    <width>28</width>
    <height>48</height>
  </char>
  <!-- P -->
  <char id="P">
    <x>978</x>
    <y>8</y>
    <width>28</width>
    <height>48</height>
  </char>
  <!-- R -->
  <char id="R">
    <x>1042</x>
    <y>8</y>
    <width>28</width>
    <height>48</height>
  </char>
  <!-- T -->
  <char id="T">
    <x>1106</x>
    <y>8</y>
    <width>28</width>
    <height>48</height>
  </char>
  <!-- V -->
  <char id="V">
    <x>1170</x>
    <y>8</y>
    <width>28</width>
    <height>48</height>
  </char>
</root>